sqlalchemy_hawq/__init__.py
sqlalchemy_hawq/ddl.py
sqlalchemy_hawq/dialect.py
sqlalchemy_hawq/partition.py
sqlalchemy_hawq/point.py
sqlalchemy_oushudb/__init__.py
sqlalchemy_oushudb/ddl.py
sqlalchemy_oushudb/dialect.py
sqlalchemy_oushudb/partition.py
sqlalchemy_oushudb/point.py
test/__init__.py
test/conftest.py
test/requirements.py
test/test_create_all.py
test/test_ddl.py
test/test_live_connection.py
test/test_suite.py
sqlalchemy_oushudb-0.0.1.dist-info/LICENSE
sqlalchemy_oushudb-0.0.1.dist-info/METADATA
sqlalchemy_oushudb-0.0.1.dist-info/WHEEL
sqlalchemy_oushudb-0.0.1.dist-info/dependency_links.txt
sqlalchemy_oushudb-0.0.1.dist-info/entry_points.txt
sqlalchemy_oushudb-0.0.1.dist-info/top_level.txt
sqlalchemy_oushudb-0.0.1.dist-info/RECORD
